Metadata-Version: 2.1
Name: hand-star
Version: 1.0.0
Summary: Handstar using Mediapipe and OpenCV Making Handdetection Easy
Home-page: https://github.com/RAJPUTRoCkStAr/hand-star
Author: Sumit Kumar Singh
Author-email: sumitsingh9441@gmail.com
License: MIT
License-File: LICENSE
Requires-Dist: opencv-python
Requires-Dist: mediapipe
